pyCDM4F/ChillDay.py
pyCDM4F/Preprocessing.py
pyCDM4F/Variables.py
pyCDM4F/__init__.py
pyCDM4F/Data/Apricot_phenology_data.csv
pyCDM4F/Data/Forsythia_phenology_data.csv
pyCDM4F/Data/Pear_phenology_data.csv
pyCDM4F/Data/Prunus_phenology_data.csv
pyCDM4F/Data/daily_temperature_data.csv
pyCDM4F/Data/monthly_meteorological_data.csv
pycdm4f-0.0.15.dist-info/licenses/LICENSE
pycdm4f-0.0.15.dist-info/METADATA
pycdm4f-0.0.15.dist-info/WHEEL
pycdm4f-0.0.15.dist-info/top_level.txt
pycdm4f-0.0.15.dist-info/RECORD
