Metadata-Version: 2.4
Name: pyCDM4F
Version: 0.0.15
Summary: Package for Predicting Plant Phenology with ChillDay-Model(CDM), which has Parameter Examination, Visualization, Clustering and so on... with Phenology & Meteorological Data.
Home-page: https://github.com/CSBL-urap/2024-summer-swkim
Author: Songwon Kim
Author-email: kimsongwon10@korea.ac.kr
License: MIT
Classifier: Programming Language :: Python :: 3
Classifier: License :: OSI Approved :: MIT License
Classifier: Operating System :: OS Independent
Requires-Python: >=3.6
License-File: LICENSE
Requires-Dist: asttokens==3.0.0
Requires-Dist: attrs==24.3.0
Requires-Dist: backcall==0.2.0
Requires-Dist: backports.tarfile==1.2.0
Requires-Dist: beautifulsoup4==4.12.3
Requires-Dist: bleach==6.1.0
Requires-Dist: bs4==0.0.2
Requires-Dist: certifi==2024.6.2
Requires-Dist: charset-normalizer==3.3.2
Requires-Dist: colorama==0.4.6
Requires-Dist: contourpy==1.1.1
Requires-Dist: cycler==0.12.1
Requires-Dist: decorator==5.1.1
Requires-Dist: defusedxml==0.7.1
Requires-Dist: docopt==0.6.2
Requires-Dist: docutils==0.20.1
Requires-Dist: et-xmlfile==1.1.0
Requires-Dist: executing==2.1.0
Requires-Dist: fastjsonschema==2.21.1
Requires-Dist: fonttools==4.53.1
Requires-Dist: idna==3.7
Requires-Dist: importlib_metadata==8.5.0
Requires-Dist: importlib_resources==6.4.0
Requires-Dist: ipython==8.12.3
Requires-Dist: jaraco.classes==3.4.0
Requires-Dist: jaraco.context==6.0.1
Requires-Dist: jaraco.functools==4.1.0
Requires-Dist: jedi==0.19.2
Requires-Dist: Jinja2==3.1.5
Requires-Dist: joblib==1.4.2
Requires-Dist: jsonschema==4.23.0
Requires-Dist: jsonschema-specifications==2023.12.1
Requires-Dist: jupyter_client==8.6.3
Requires-Dist: jupyter_core==5.7.2
Requires-Dist: jupyterlab_pygments==0.3.0
Requires-Dist: keyring==25.5.0
Requires-Dist: kiwisolver==1.4.5
Requires-Dist: lxml==5.3.0
Requires-Dist: markdown-it-py==3.0.0
Requires-Dist: MarkupSafe==2.1.5
Requires-Dist: matplotlib==3.7.5
Requires-Dist: matplotlib-inline==0.1.7
Requires-Dist: mdurl==0.1.2
Requires-Dist: mistune==3.1.0
Requires-Dist: more-itertools==10.5.0
Requires-Dist: nbclient==0.10.1
Requires-Dist: nbconvert==7.16.5
Requires-Dist: nbformat==5.10.4
Requires-Dist: nh3==0.2.20
Requires-Dist: numpy==1.24.4
Requires-Dist: openpyxl==3.1.5
Requires-Dist: packaging==24.1
Requires-Dist: pandas==2.0.3
Requires-Dist: pandocfilters==1.5.1
Requires-Dist: parso==0.8.4
Requires-Dist: patsy==0.5.6
Requires-Dist: pickleshare==0.7.5
Requires-Dist: pillow==10.4.0
Requires-Dist: pip==24.3.1
Requires-Dist: pipreqs==0.5.0
Requires-Dist: pkginfo==1.12.0
Requires-Dist: pkgutil_resolve_name==1.3.10
Requires-Dist: platformdirs==4.3.6
Requires-Dist: prompt_toolkit==3.0.48
Requires-Dist: pure_eval==0.2.3
Requires-Dist: Pygments==2.19.0
Requires-Dist: pyparsing==3.1.2
Requires-Dist: python-dateutil==2.9.0.post0
Requires-Dist: pytz==2024.1
Requires-Dist: pywin32==308
Requires-Dist: pywin32-ctypes==0.2.3
Requires-Dist: pyzmq==26.2.0
Requires-Dist: readme_renderer==43.0
Requires-Dist: referencing==0.35.1
Requires-Dist: requests==2.32.3
Requires-Dist: requests-toolbelt==1.0.0
Requires-Dist: rfc3986==2.0.0
Requires-Dist: rich==13.9.4
Requires-Dist: rpds-py==0.20.1
Requires-Dist: scikit-learn==1.3.2
Requires-Dist: scipy==1.10.1
Requires-Dist: seaborn==0.13.2
Requires-Dist: setuptools==75.3.0
Requires-Dist: six==1.16.0
Requires-Dist: soupsieve==2.5
Requires-Dist: stack-data==0.6.3
Requires-Dist: statsmodels==0.14.1
Requires-Dist: test-py==0.3
Requires-Dist: threadpoolctl==3.5.0
Requires-Dist: tinycss2==1.2.1
Requires-Dist: tornado==6.4.2
Requires-Dist: tqdm==4.67.1
Requires-Dist: traitlets==5.14.3
Requires-Dist: twine==6.0.1
Requires-Dist: typing_extensions==4.12.2
Requires-Dist: tzdata==2024.1
Requires-Dist: urllib3==2.2.2
Requires-Dist: wcwidth==0.2.13
Requires-Dist: webencodings==0.5.1
Requires-Dist: wheel==0.44.0
Requires-Dist: yarg==0.1.9
Requires-Dist: zipp==3.20.2
Dynamic: author
Dynamic: author-email
Dynamic: classifier
Dynamic: description
Dynamic: description-content-type
Dynamic: home-page
Dynamic: license
Dynamic: license-file
Dynamic: requires-dist
Dynamic: requires-python
Dynamic: summary
